Workbook

Sheet 1. Financial Structure Analysis
B1: Shell 2024 and 2023
B3: Abbreviations | E3: Name: THI MINH THUAN PHUNG Student number: 20115516
B4: Statement of Financial Position (Balance Sheet) | C4: SFP
B5: Income Statement | C5: I/S
B6: Statement of cashflow | C6: SCF
B8: All $ figures in millions unless specifed otherwise | C8: Million $
B10: Financial Structure Analysis
A12: W1 | B12: Liabilities/Debt
C13: 2024 | D13: 2023 | F13: Page 242
B14: Current Debt | C14: 11630 | D14: 9931 | F14: SFP
B15: Non-current Debt (long term) | C15: 65448 | D15: 71610 | F15: SFP
B16: Total Debt | C16: =SUM(C14:C15) -> 77078 | D16: =SUM(D14:D15) -> 81541
B17: Cash and cash equivalents | C17: 39110 | D17: 38774 | F17: SPF, Note 21 debt, page 286
B18: Net Debt | C18: =C16-C17 +841 -> 38809 | D18: =D16-D17 +775 -> 43542
B20: Equity | C20: 180168 | D20: 188362 | F20: SFP
B22: Total Finance Capital | C22: =C18+C20 -> 218977 | D22: =D18+D20 -> 231904
B24: Gearing | C24: =C18/C22 -> 0.17722866 | D24: =D18/D22 -> 0.18775873
A28: W2 | B28: Maturity Profile of Debt | C28: 2024 | D28: 2023 | E28: 2024 | F28: 2023 | G28: Note 21, Page 285
E29: % of Borrowings
B30: Under 1 year | C30: 6921 | D30: 5352 | E30: =C30/$C$38 -> 0.22726079 | F30: =D30/$D$38 -> 0.15583508
B31: 1 to 2 years | C31: 3961 | D31: 6424 | E31: =C31/$C$38 -> 0.13006502 | F31: =D31/$D$38 -> 0.18704868
B32: 2 to 3 years | C32: 2413 | D32: 3929 | E32: =C32/$C$38 -> 0.079234255 | F32: =D32/$D$38 -> 0.11440135
B33: 3 to 4 years | C33: 5496 | D33: 2835 | E33: =C33/$C$38 -> 0.1804689 | F33: =D33/$D$38 -> 0.08254717
B34: 4 to 5 years | C34: 2365 | D34: 5495 | E34: =C34/$C$38 -> 0.077658107 | F34: =D34/$D$38 -> 0.15999884
B35: Over 5 | C35: 27615 | D35: 30365 | E35: =C35/$C$38 -> 0.90677743 | F35: =D35/$D$38 -> 0.88414279
B36: Total Repayments | C36: =SUM(C30:C35) -> 48771 | D36: =SUM(D30:D35) -> 54400
B37: Interest | C37: -18317 | D37: -20056
B38: Total Debt | C38: =SUM(C36:C37) -> 30454 | D38: =SUM(D36:D37) -> 34344
A42: W3 | B42: Other workings
B43: Fixed versus variable | C43: 2024 | D43: 2023
B44: Fixed Debt | C44: Notdisclosed | D44: Notdisclosed
B45: Variable Debt | C45: Notdisclosed | D45: Notdisclosed
C46: Most debt is raised from central borrowing programmes. Shell's policy is to have debt principally denominated in dollars and to retain a balanced exposure to fixed and floating rates over time. Shell has issued a significant amount of fixed rate debt in recent years, taking advantage of historically low interest rates. As a result, the majority of the debt portfolio at December 31, 2024, is fixed | F46: Note 26, Page 299
A50: W4 | B50: Currency Profile of Debt | C50: 2024 | D50: 2023
B51: GBP | C51: Notdisclosed | D51: Notdisclosed | F51: Page 141
B52: EUR | C52: Notdisclosed | D52: Notdisclosed | F52: Note 26 page 301
B53: Other
A58: W5 | B58: Sensitivity of Rates | C58: 2024 | D58: 2023
B59: Movement in rates | C59: =-69+98+34-103+30 -> -10 | D59: =-270-46+49-129+9 -> -387 | F59: Note 26, Page 302
B60: Movement in exchange rates (proxy; sum of 10% appreciation vs USD across listed currencies)
B61: as % of Operating profit (loss) (income before taxation - interest expense ) | C61: =C59/(29922 +4787) -> -0.00028810971 | D61: =D59/(32627+4673) -> -0.010375335 | F61: Op Profit: IS
B62: as % of total equity | C62: =C59/C20 -> -5.5503752e-05 | D62: =D59/D20 -> -0.0020545545 | F62: Equity: SFP
A66: W6 | B66: Undrawn Committed Facility | C66: 2024 | D66: 2023
B67: Total amount | C67: 8000 | D67: 8000 | F67: Note 21, Page 287
B68: As % of net debt | C68: =C67/C18 -> 0.20613775 | D68: =D67/D18 -> 0.18373065 | F68: Equity: SFP
B69: As % of total assets | C69: =C67/387609 -> 0.020639356 | D69: =D67/406270 -> 0.019691338 | F69: Assets: SFP
A73: W7 | B73: Cash Flow Impacts | C73: 2024 | D73: 2023
B74: Cash from operations | C74: 54687 | D74: 54191 | F74: SCF | G74: Page 246
B75: Interest Paid | C75: 4557 | D75: 4441 | F75: SCF
B77: New borrowings | C77: 363 | D77: 1029 | F77: SCF
B78: Repayment of borrowings | C78: 9672 | D78: 10650 | F78: SCF
B79: Net cash movement | C79: =SUM(C77:C78) -> 10035 | D79: =SUM(D77:D78) -> 11679
A83: W8 | B83: Debt servicing ability | C83: 2024 | D83: 2023
B84: Interest Paid From Operations | C84: =C75/C74 -> 0.083328762 | D84: =D75/D74 -> 0.081950877 | F84: See W6
B85: Interest Paid to Operating Profit | C85: =C75/(29922 +4787) -> 0.1312916 | D85: =D75/(32627+4673) -> 0.11906166 | F85: Op Profit: IS
B87: Net Debt | C87: =C18 -> 38809 | D87: =D18 -> 43542 | F87: See W1
B88: Net Debt to Operating Cash | C88: =C87/C74 -> 0.70965677 | D88: =D87/D74 -> 0.80349135
B90: Free Cash Flow (see below) | C90: =C99 -> 32150 | D90: =D99 -> 29322
B91: Net Debt to Free Cash Flow | C91: =C87/C90 -> 1.2071229 | D91: =D87/D90 -> 1.4849601
B93: Free Cash Flow | C93: 2024 | D93: 2023
B94: Cash Inflow from Operations | C94: =C74 -> 54687 | D94: =D74 -> 54191 | F94: SCF
B95: Less Interest Paid | C95: =-C75 -> -4557 | D95: =-D75 -> -4441 | F95: See W6
B96: Less Capital Expenditure | C96: -19601 | D96: -22993 | F96: SCF
B97: Less Payments to buy Intangible Assets | C97: Notdisclosed | D97: Notdisclosed | F97: SCF
B98: Add Disposals of PPE and Intangible Assets | C98: 1621 | D98: 2565 | F98: SCF, Page 246
C99: =SUM(C94:C98) -> 32150 | D99: =SUM(D94:D98) -> 29322
A103: W9 | B103: Commitments | C103: 2024 | D103: 2023
B104: Contractual commitments (Capital Commitments ) | C104: 7815 | D104: 12419 | F104: Note 12, page 278
B106: As % of total assets | C106: =C104/387609 -> 0.020162071 | D106: =D104/406270 -> 0.030568341 | F106: Assets: SFP
A110: W10 | B110: Guarantees | C110: 2024 | D110: 2023
B111: Performance and Payment Bonds | C111: Not disclosed | D111: Not disclosed
B112: Guarantees | C112: Not disclosed | D112: Not disclosed
A117: W11 | B117: Working Capital | C117: 2024 | D117: 2023 | L117: Page 242
B118: Trade and other payables | C118: 60693 | D118: 68237 | F118: SFP
B119: Decommissioning and other provisions | C119: 4469 | D119: 4041 | F119: SFP
B120: Income taxes payable | C120: 4648 | D120: 3422 | F120: SFP
B121: Short term cash requirements | C121: =SUM(C118:C120) -> 69810 | D121: =SUM(D118:D120) -> 75700
B123: Receviables | C123: 45860 | D123: 53273 | F123: SFP
B124: Inventory | C124: 23426 | D124: 26019 | F124: SFP
B125: Cash | C125: 39110 | D125: 38774 | F125: SFP
B126: Other Investments | C126: - | D126: - | F126: SFP
B127: Short term cash availability | C127: =SUM(C123:C126) -> 108396 | D127: =SUM(D123:D126) -> 118066
B129: Cash Generation | C129: 2024 | D129: 2023
B130: Opening Receivables | C130: =D123 -> 53273 | D130: 66510 | F130: SFP
B131: Revenue | C131: 284312 | D131: 316620 | F131: I/S | L131: Page 241
B132: Less: Closing Receivables | C132: -45860 | D132: -53273 | F132: SFP
B133: Cash from Sales (per annum) | C133: =SUM(C130:C132) -> 291725 | D133: =SUM(D130:D132) -> 329857
B134: Cash from Sales (per month) | C134: =C133/12 -> 24310.417 | D134: =D133/12 -> 27488.083
A138: W12 | B138: Equity | C138: 2024 | D138: 2023
B139: Market Value of Equity at year end ($) | C139: 203180 | D139: 229340 | F139: https://stockanalysis.com/stocks/shel/market-cap/
F140: Euro Exchange Rates | Central Bank of Ireland
B142: Book Value of Equity | C142: =C20 -> 180168 | D142: =D20 -> 188362 | F142: SFP
B143: Market (Value) to Book (Value) | C143: =C139/C142 -> 1.1277252 | D143: =D139/D142 -> 1.2175492
B146: Net Debt | C146: =C18 -> 38809 | D146: =D18 -> 43542 | F146: See W1
B147: Equity | C147: =C20 -> 180168 | D147: =D20 -> 188362 | F147: SFP
B148: Total Finance Capital | C148: =SUM(C146:C147) -> 218977 | D148: =SUM(D146:D147) -> 231904 | F148: SFP
B149: % Equity | C149: =C147/C148 -> 0.82277134 | D149: =D147/D148 -> 0.81224127
A153: W13 | B153: Total Shareholder Return | C153: 2024 | D153: 2023
B154: Opening Share price on 1/1/2024 & 2023 [GBp] | C154: 2571 | D154: 2326 | F154: https://uk.finance.yahoo.com/quote/SHEL.L/history/?utm_source=chatgpt.com&period1=1672358400&period2=1735689600
B155: Closing Share price on 31/12/2024 & 2023 [GBp] | C155: 2476 | D155: 2569
...

Sheet 1. AR Screenshot
A1: 1. Financial Structure Analysis Screenshot

Sheet 2. Assest and Operational Analy
B1: Shell 2024 and 2023
B3: Abbreviations | E3: Source is noted where applicable
B4: Statement of Financial Position (Balance Sheet) | C4: SFP
B5: Income Statement | C5: I/S
B6: Statement of cashflow | C6: SCF
B12: ASSET PERFORMANCE ANALYSIS
A14: W15 | B14: Non-Current Assets Base - Growth Rate
D15: 2024 | F15: 2023 | H15: 2022 | I15: page 244
B16: Total Non Current Assets | D16: 259683 | F16: 272155 | H16: 277086 | I16: SFP
B17: Growth Rate | D17: =D16/F16-1 -> -0.045826827 | F17: =F16/H16-1 -> -0.017795919
A21: W16 | B21: Strength of Balance Sheet - % Intangibles | D21: 2024 | F21: 2023 | I21: page 244
B22: Intangible Assets | D22: 9480 | E22: =D22/D23 -> 0.036506048 | F22: 10253 | G22: =F22/F23 -> 0.037673385 | I22: SFP
B23: Total Non-Current Assets | D23: 259683 | F23: 272155 | I23: SFP
B25: Goodwill | D25: 16032 | E25: =D25/D26 -> 0.06173681 | F25: 16660 | G25: =F25/F26 -> 0.061215116 | I25: SFP
B26: Total Non-Current Assets | D26: 259683 | F26: 272155 | I26: SFP
A30: W17 | B30: Asset Performance - Profit Based Measures
B31: RoA | D31: 2024 | F31: 2023
B32: Earnings Before Interest and Tax (operating profit) | D32: =(29922 +4787) -> 34709 | E32: =D32/D33 -> 0.089546424 | F32: =(32627+4673) -> 37300 | G32: =F32/F33 -> 0.091810865 | I32: I/S | Q32: Earnings Before Interest and Tax = Income before taxation + interest expense
B33: Total Assets | D33: 387609 | F33: 406270 | I33: SFP
B35: Return on Non-Current Assets | D35: =D3 -> 0
B36: Earnings Before Interest and Tax | D36: =D32 -> 34709 | E36: =D36/D37 -> 0.13365912 | F36: =F32 -> 37300 | G36: =F36/F37 -> 0.13705425 | I36: I/S
B37: Total Non-Current Assets | D37: 259683 | F37: 272155 | I37: SFP
B39: ROCE
B40: Earnings Before Interest and Tax | D40: =D32 -> 34709 | E40: =D40/D41 -> 0.11616987 | F40: =F32 -> 37300 | G40: =F40/F41 -> 0.11989329 | I40: I/S
B41: Total Assets - Current Liabilities | D41: =D33-88831 -> 298778 | F41: =F33-95160 -> 311110 | I41: SFP
B43: ROCE version 2
B44: Earnings Before Interest and Tax - Non-recurring items | D44: =D32-47 -> 34662 | E44: =D44/D45 -> 0.11601256 | F44: =F32-(-201) -> 37501 | G44: =F44/F45 -> 0.12053936 | I44: I/S
B45: Total Assets - Current Liabilities | D45: =D41 -> 298778 | F45: =F41 -> 311110 | I45: SFP
A49: W18 | B49: Asset Performance - Revenue Based Measures | D49: 2024 | F49: 2023
B50: Asset Turnover
B51: Revenue | D51: 284312 | E51: =D51/D52 -> 0.73350206 | F51: 316620 | G51: =F51/F52 -> 0.77933394 | I51: I/S
B52: Total Assets | D52: =D33 -> 387609 | F52: =F33 -> 406270 | I52: SFP
A56: W19 | B56: Asset Performance - Employee Based Measures | D56: 2024 | F56: 2023
B57: Revenue per Employee
B58: Revenue | D58: =D51 -> 284312 | E58: =(D58/D59)*1000000 -> 2961583.3 | F58: =F51 -> 316620 | G58: =(F58/F59)*1000000 -> 3073980.6 | I58: I/S
B59: Total No of Employees | D59: 96000 | F59: 103000 | I59: page 117
B61: Average cost per employee
B62: Total Wages | D62: 10928 | E62: =D62/D63 * 1000000 -> 113833.33 | F62: 10648 | G62: =F62/F63 * 1000000 -> 103378.64 | I62: Note 33, page 313
B63: Total No of Employees | D63: 96000 | F63: 103000
B67: OPERATIONAL ANALYSIS
A69: W20 | B69: Sales Analysis
B70: Profit | D70: 2024 | F70: 2023 | H70: Operating Profit 2022
B71: Operating Profit | D71: =D32 -> 34709 | F71: =F32 -> 37300 | H71: 64815 | I71: I/S | J71: Page 243 | L71: (Income before taxation - interest expense)
B72: Operating Profit / (Loss) Growth or (Decline) | D72: =D71/F71-1 -> -0.069463807 | F72: =F71/64815 - 1 -> -0.42451593
B74: Income for the period (Profit / (Loss) for the financial year ) | D74: 16521 | F74: 19636 | H74: 42874 | I74: I/S
B75: Profit / (Loss) Growth or (Decline) | D75: =D74/F74-1 -> -0.1586372 | F75: =F74/H74-1 -> -0.54200681
B77: Revenue | D77: =D58 -> 284312 | F77: =F58 -> 316620 | H77: 381314 | I77: I/S
B78: Sales Growth / (Decline) | D78: =D77/F77-1 -> -0.1020403 | F78: =F77/H77-1 -> -0.1696607
A82: W21 | B82: Margin Analysis | D82: 2024 | F82: 2023
B83: Gross Margin
B84: Gross Profit | D84: Not applicable | F84: Not applicable | I84: I/S
B85: Revenue | I85: I/S
B87: Operating Margin
B88: Operating Profit | D88: =D71 -> 34709 | E88: =D88/D89 -> 0.12208067 | F88: =F71 -> 37300 | G88: =F88/F89 -> 0.11780683 | I88: I/S
B89: Revenue | D89: =D51 -> 284312 | F89: =F51 -> 316620 | I89: I/S
B91: Net Margin
B92: Profit for the year | D92: =D74 -> 16521 | E92: =D92/D93 -> 0.058108697 | F92: =F74 -> 19636 | G92: =F92/F93 -> 0.06201756 | I92: I/S
B93: Revenue | D93: =D51 -> 284312 | F93: =F51 -> 316620 | I93: I/S
B97: SEGMENT ANALYSIS
A100: W22 | D100: 2024 | F100: 2023
B101: Business Segment Analysis | D101: Segment earnings | E101: % Share | F101: Segment earnings | G101: % Share | H101: Growth / (Decline) $
B102: Integrated Gas | D102: 9590 | E102: =D102/$D$108 -> 0.57110529 | F102: 7057 | G102: =F102/$F$108 -> 0.34796115 | H102: =(D102-F102)/F102 -> 0.35893439
B103: Upstream | D103: 7772 | E103: =D103/$D$108 -> 0.46283945 | F103: 8540 | G103: =F103/$F$108 -> 0.42108377 | H103: =(D103-F103)/F103 -> -0.089929742
B104: Marketing | D104: 1894 | E104: =D104/$D$108 -> 0.11279181 | F104: 3057 | G104: =F104/$F$108 -> 0.15073221 | H104: =(D104-F104)/F104 -> -0.38043834
B105: Chemicals and Products | D105: 1757 | E105: =D105/$D$108 -> 0.10463316 | F105: 1482 | G105: =F105/$F$108 -> 0.07307332 | H105: =(D105-F105)/F105 -> 0.18556005
B106: Renewables and Energy Solutions | D106: -1229 | E106: =D106/$D$108 -> -0.073189614 | F106: 3089 | G106: =F106/$F$108 -> 0.15231004 | H106: =(D106-F106)/F106 -> -1.3978634
B107: Corporate | D107: -2992 | E107: =D107/$D$108 -> -0.17818009 | F107: -2944 | G107: =F107/$F$108 -> -0.1451605 | H107: =(D107-F107)/F107 -> 0.016304348
D108: =SUM(D102:D107) -> 16792 | E108: =D108/$D$108 -> 1 | F108: =SUM(F102:F107) -> 20281 | G108: =F108/$F$108 -> 1 | H108: =(D108-F108)/F108 -> -0.17203294
A112: W23 | D112: 2024 | F112: 2023
B113: Business Segment Analysis | D113: Adjusted EBITDA | E113: % Share | F113: Adjusted EBITDA | G113: % Share | H113: Growth / (Decline) $
B114: Integrated Gas | D114: 20978 | E114: =D114/$D$120 -> 0.31879521 | F114: 23773 | G114: =F114/$F$120 -> 0.34685868 | H114: =(D114-F114)/F114 -> -0.11757035 | I114: Page 35
B115: Upstream | D115: 31264 | E115: =D115/$D$120 -> 0.4751079 | F115: 30622 | G115: =F115/$F$120 -> 0.44678864 | H115: =(D115-F115)/F115 -> 0.020965319 | I115: Page 41
B116: Marketing | D116: 7476 | E116: =D116/$D$120 -> 0.11361011 | F116: 6337 | G116: =F116/$F$120 -> 0.092459657 | H116: =(D116-F116)/F116 -> 0.17973805 | I116: Page 59
B117: Chemicals and Products | D117: 6783 | E117: =D117/$D$120 -> 0.10307884 | F117: 7489 | G117: =F117/$F$120 -> 0.10926785 | H117: =(D117-F117)/F117 -> -0.094271598 | I117: Page 63
B118: Renewables and Energy Solutions | D118: -22 | E118: =D118/$D$120 -> -0.00033432618 | F118: 1481 | G118: =F118/$F$120 -> 0.021608451 | H118: =(D118-F118)/F118 -> -1.0148548 | I118: Page 71
B119: Corporate | D119: -675 | E119: =D119/$D$120 -> -0.010257735 | F119: -1164 | G119: =F119/$F$120 -> -0.016983279 | H119: =(D119-F119)/F119 -> -0.42010309 | I119: Page 75
D120: =SUM(D114:D119) -> 65804 | E120: =D120/$D$120 -> 1 | F120: =SUM(F114:F119) -> 68538 | G120: =F120/$F$120 -> 1 | H120: =(D120-F120)/F120 -> -0.03989028
B122: EBITDA: Earnings before Interest, Tax, Depreciation and Amortisation
A126: W24 | D126: 2024 | F126: 2023
B127: Business Segment Analysis | D127: Capital Expenditure | E127: % Share | F127: Capital Expenditure | G127: % Share | H127: Growth / (Decline) $
B128: Integrated Gas | D128: 4095 | E128: =D128/$D$134 -> 0.20891791 | F128: 3491 | G128: =F128/$F$134 -> 0.15182882 | H128: =(D128-F128)/F128 -> 0.17301633 | I128: Note 7, page 274
B129: Upstream | D129: 7739 | E129: =D129/$D$134 -> 0.39482679 | F129: 8249 | G129: =F129/$F$134 -> 0.35876136 | H129: =(D129-F129)/F129 -> -0.061825676
B130: Marketing | D130: 2357 | E130: =D130/$D$134 -> 0.12024897 | F130: 5741 | G130: =F130/$F$134 -> 0.24968469 | H130: =(D130-F130)/F130 -> -0.58944435
B131: Chemicals and Products | D131: 2943 | E131: =D131/$D$134 -> 0.1501454 | F131: 2928 | G131: =F131/$F$134 -> 0.1273431 | H131: =(D131-F131)/F131 -> 0.0051229508
B132: Renewables and Energy Solutions | D132: 2338 | E132: =D132/$D$134 -> 0.11927963 | F132: 2314 | G132: =F132/$F$134 -> 0.10063933 | H132: =(D132-F132)/F132 -> 0.010371651
B133: Corporate | D133: 129 | E133: =D133/$D$134 -> 0.0065812969 | F133: 270 | G133: =F133/$F$134 -> 0.011742704 | H133: =(D133-F133)/F133 -> -0.52222222
D134: =SUM(D128:D133) -> 19601 | E134: =D134/$D$134 -> 1 | F134: =SUM(F128:F133) -> 22993 | G134: =F134/$F$134 -> 1 | H134: =(D134-F134)/F134 -> -0.14752316
A138: W25 | D138: 2024 | F138: 2023
B139: Business Segment Analysis | D139: Cash flow from operating activities | E139: % Share | F139: Cash flow from operating activities | G139: % Share | H139: Growth / (Decline) $
B140: Integrated Gas | D140: 16909 | E140: =D140/$D$146 -> 0.30920728 | F140: 17520 | G140: =F140/$F$146 -> 0.32327109 | H140: =(D140-F140)/F140 -> -0.034874429
B141: Upstream | D141: 21244 | E141: =D141/$D$146 -> 0.38847947 | F141: 21450 | G141: =F141/$F$146 -> 0.39578567 | H141: =(D141-F141)/F141 -> -0.0096037296
B142: Marketing | D142: 7363 | E142: =D142/$D$146 -> 0.13464387 | F142: 5561 | G142: =F142/$F$146 -> 0.10260905 | H142: =(D142-F142)/F142 -> 0.32404244
B143: Chemicals and Products | D143: 7253 | E143: =D143/$D$146 -> 0.13263235 | F143: 7513 | G143: =F143/$F$146 -> 0.13862647 | H143: =(D143-F143)/F143 -> -0.034606682
B144: Renewables and Energy Solutions | D144: 3798 | E144: =D144/$D$146 -> 0.069452318 | F144: 2984 | G144: =F144/$F$146 -> 0.055059414 | H144: =(D144-F144)/F144 -> 0.2727882
B145: Corporate | D145: -1882 | E145: =D145/$D$146 -> -0.034415288 | F145: -832 | G145: =F145/$F$146 -> -0.015351686 | H145: =(D145-F145)/F145 -> 1.2620192
D146: =SUM(D140:D145) -> 54685 | E146: =D146/$D$146 -> 1 | F146: =SUM(F140:F145) -> 54196 | G146: =F146/$F$146 -> 1 | H146: =(D146-F146)/F146 -> 0.0090228061
A150: W26 | D150: 2024 | F150: 2023
B151: Business Segment Analysis | D151: Revenue | E151: % Share | F151: Revenue | G151: % Share | H151: Growth / (Decline) $
B152: Integrated Gas | D152: 37290 | E152: =D152/$D$158 -> 0.13115873 | F152: 37645 | G152: =F152/$F$158 -> 0.11889647 | H152: =(D152-F152)/F152 -> -0.0094302032 | I152: Note 7 page 271
B153: Upstream | D153: 6606 | E153: =D153/$D$158 -> 0.023235038 | F153: 6475 | G153: =F153/$F$158 -> 0.020450382 | H153: =(D153-F153)/F153 -> 0.02023166
...

Sheet 2. AR Screenshot
A2: 2. Assest and Operational Analysis screenshot

Sheet 3. Cash flow analysis
B1: Shell 2024 and 2023
B3: Abbreviations | F3: Source is noted where applicable
B4: Statement of Financial Position (Balance Sheet) | D4: SFP
B5: Income Statement | D5: I/S
B6: Statement of cashflow | D6: SCF
B8: All $ figures in millions unless specifed otherwise
B12: CASH FLOW ANALYSIS
A14: W27 | B14: Headline Analysis - | D14: 2024 | F14: 2023
B15: Cash Inflow from Operations | D15: 54687 | F15: 54191 | J15: SCF
B16: Cash Inflow / (Outflow) from Investing Activities | D16: -15155 | F16: -17734 | J16: SCF
B17: Cash (Outflow) from Financing Activities | D17: -38435 | F17: -38235 | J17: SCF
B18: Net Cash Movement | D18: =SUM(D15:D17) -> 1097 | F18: =SUM(F15:F17) -> -1778
B22: Cash Flow from Operating Activties
A24: W28 | B24: Net Cash Flow From Operations | D24: 2024 | F24: 2023 | H24: 2022
B25: Net Cash Flow From Operations | D25: =D15 -> 54687 | F25: =F15 -> 54191 | H25: 68414 | J25: SCF
B26: Change % | D26: =D25/F25-1 -> 0.0091528114 | F26: =F25/H25-1 -> -0.20789604
B28: Net Cash Flow From Operations | D28: =D15 -> 54687 | F28: =F15 -> 54191 | J28: SCF
B29: Operating Profit / (Loss) | D29: ='2. Assest and Operational Analy'!D71 -> 34709 | F29: ='2. Assest and Operational Analy'!F71 -> 37300 | J29: I/S
B30: Cash Flow great than profits | D30: Yes | F30: Yes | H30: Yes
A34: W29 | B34: Operating Cash Margin | D34: 2024 | F34: 2023
B35: Operating Cash Flow | D35: =D15 -> 54687 | E35: =D35/D36 -> 0.19234855 | F35: =F15 -> 54191 | G35: =F35/F36 -> 0.1711547 | J35: SCF
B36: Revenue | D36: ='2. Assest and Operational Analy'!D89 -> 284312 | F36: ='2. Assest and Operational Analy'!F89 -> 316620 | J36: I/S
A40: W30 | B40: Net Debt to Cash Flow | D40: 2024 | F40: 2023
B41: Net Debt | D41: ='1. Financial Structure Analysis'!C18 -> 38809 | E41: =D41/D42 -> 0.70965677 | F41: ='1. Financial Structure Analysis'!D18 -> 43542 | G41: =F41/F42 -> 0.80349135 | J41: Page 244
B42: Operating Cashflow | D42: =D15 -> 54687 | E42: Years | F42: =F15 -> 54191 | G42: Years | J42: SCF
B44: Interest Servicing Ability | D44: 2024 | F44: 2023
B45: Interest Paid | D45: 4557 | E45: =D45/D46 -> 0.083328762 | F45: 4441 | G45: =F45/F46 -> 0.081950877
B46: Operating Cash Flow | D46: =D15 -> 54687 | F46: =F15 -> 54191 | J46: SCF
B48: Interest Rate - estimate | D48: 2024 | F48: 2023
B49: Interest Paid | D49: =D45 -> 4557 | E49: =D49/D50 -> 0.059121928 | F49: =F45 -> 4441 | G49: =F49/F50 -> 0.054463399
B50: Total Debt | D50: ='1. Financial Structure Analysis'!C16 -> 77078 | F50: ='1. Financial Structure Analysis'!D16 -> 81541
B54: Cash Flow from Investing Activties
A56: W31 | B56: Replacement Rate | D56: 2024 | F56: 2023
B57: PPE | D57: 185219 | F57: 194835 | H57: SFP | I57: Page 242
B58: Intangibles | D58: 9480 | F58: 10253 | H58: SFP | I58: Note 12 page 275
D59: =SUM(D57:D58) -> 194699 | F59: =SUM(F57:F58) -> 205088
B61: Additions to PPE | D61: 26446 | F61: 25831 | H61: Note 12, Page 383 | I61: Page 383
B62: Additions to Intangibles | D62: 4456 | F62: 5558 | H62: Note 12, Page 383
D63: =SUM(D61:D62) -> 30902 | F63: =SUM(F61:F62) -> 31389
B65: Replacement Rate (notional years) | D65: =D59/D63 -> 6.3005307 | F65: =F59/F63 -> 6.5337539
B67: Capital expenditure | D67: 19601 | F67: 22993
B73: Ability to Reinvest
D74: 2024 | F74: 2023
B75: Net Cash Flow From Operations | D75: =D25 -> 54687 | F75: =F25 -> 54191 | H75: SCF
B76: Payments on PPE and Intangibles | D76: =D67 -> 19601 | F76: =F67 -> 22993 | H76: SCF
B78: Reinvestment period required | D78: =D75/D76 -> 2.7900107 | F78: =F75/F76 -> 2.3568477
B81: Strategic Expansion/Contraction | D81: 2024 | F81: 2023
B82: Investments in joint ventures and associates | D82: -1404 | F82: -1202 | H82: SCF
B83: Proceeds from joint ventures and associates from sale, capital reduction and repayment of long-term loans | D83: 590 | F83: 474 | H83: SCF
B84: Investments in equity securities | D84: -80 | F84: -197 | H84: SCF
B85: Proceeds from sale of equity securities | D85: 582 | F85: 51 | H85: SCF
D86: =SUM(D82:D85) -> -312 | F86: =SUM(F82:F85) -> -874
B90: Cash Flow from Financing Activties
A92: W32 | B92: Debt and Equity | D92: 2024 | F92: 2023
B93: Debt - Interest | D93: =- D45 -> -4557 | F93: =- F45 -> -4441 | H93: SCF
B94: Debt - Movement in short term | H94: SCF
B95: Debt - Proceeds - Long term | H95: SCF
B96: Repayment of loans | D96: -9672 | F96: -10650
B97: Total Debt | D97: =SUM(D93:D96) -> -14229 | F97: =SUM(F93:F96) -> -15091
B99: Cash dividends paid to:Shell plc shareholders | D99: -8668 | F99: -8393 | H99: SCF
B100: Equity - Purchase of treasury shares | D100: -13898 | F100: -14617 | H100: SCF
B101: Equity - Share issue
B102: Total Equity | D102: =SUM(D99:D101) -> -22566 | F102: =SUM(F99:F101) -> -23010
A106: W33 | B106: Dividend Yield | D106: 2024 | F106: 2023
B107: Equity - dividends | D107: 8668 | F107: 8393 | H107: SCF
B108: Market Value of Equity at year end ($) | D108: ='1. Financial Structure Analysis'!C139 -> 203180 | F108: ='1. Financial Structure Analysis'!D139 -> 229340 | H108: Financial structure analysis, W12
B110: Dividend Yield (Div/Market Value) | D110: =D107/D108 -> 0.042661679 | F110: =F107/F108 -> 0.03659632
A114: W34 | B114: Free Cash Flow | D114: 2024 | F114: 2023
B115: Cash Inflow from Operations | D115: =D25 -> 54687 | E115: =E25 -> 0 | F115: =F25 -> 54191 | H115: SCF
B116: Cash Inflow / (Outflow) on Investing Activities | D116: =D16 -> -15155 | E116: =E16 -> 0 | F116: =F16 -> -17734 | H116: SCF
H117: SCF
B118: *Adjust for: Purchase of Investments | D118: Notdisclosed | F118: Notdisclosed | J118: SCF
B119: *Adjust for: Disposals of Investments | D119: Notdisclosed | F119: Notdisclosed | J119: SCF
D120: =SUM(D115:D119) -> 39532 | F120: =SUM(F115:F119) -> 36457
B121: FCF is calculated by Operating Cash Flow plus Investing Cash Flow as it consistent with Shell's reported definition (Page 21 annual report )
A125: W35 | B125: FCF Margin | D125: 2024 | F125: 2023
B126: FCF | D126: =D120 -> 39532 | E126: =D126/D127 -> 0.13904443 | F126: =F120 -> 36457 | G126: =F126/F127 -> 0.11514434 | H126: W8
B127: Revenue | D127: =D36 -> 284312 | E127: =E36 -> 0 | F127: =F36 -> 316620 | H127: I/S
B129: FCF Yield
B130: FCF | D130: =D120 -> 39532 | E130: =D130/D131 -> 0.1633628 | F130: =F120 -> 36457 | G130: =F130/F131 -> 0.13359987
B131: Market Capitalisation + Net Debt (note 1) | D131: =D137 -> 241989 | F131: =F137 -> 272882 | H131: Note 1
B133: Note 1: Market capitalisation and net debt | D133: 2024 | F133: 2023
B134: Market Value of Equity at year end ($) | D134: =D108 -> 203180 | F134: =F108 -> 229340 | H134: Financial structure analysis, W12
B135: Market Value of Equity at year end (€) | D135: NA | F135: NA | H135: Financial structure analysis, W12
B136: Net Debt | D136: =D41 -> 38809 | F136: =F41 -> 43542
B137: Market Capitalisation + Net Debt | D137: =D134+D136 -> 241989 | F137: =F134+F136 -> 272882

Sheet 3.AR Screenshot
A2: 3. Cash flow analysis screenshot

Sheet 4. CFA Valuation
B1: Shell 2024 and 2023
B3: Abbreviations | F3: Source is noted where applicable
B4: Statement of Financial Position | C4: SFP
B5: Income Statement | C5: I/S
B6: Statement of cashflow | C6: SCF
B11: VALUATION
G12: Rate 2024: GBP/USD : 1.2781 Rate 2023: GBP/USD : 1.2439
A13: W36 | B13: Market Capitalisation | C13: 2024 | E13: 2023
B15: Share price USD | C15: ='1. Financial Structure Analysis'!C155/100 *1.2781 -> 31.645756 | E15: ='1. Financial Structure Analysis'!D155/100*1.2439 -> 31.955791 | G15: W13 Finance Structure analysis
B16: No. of Shares | C16: 6115031158 | E16: 6524109049 | G16: 27. Share capital, Page 307
B17: Market Capitalisation (millions) USD | C17: =C16*C15/1000000 -> 193514.78 | E17: =E16*E15/1000000 -> 208483.07
B18: Market cap growth | C18: =(C17-E17)/E17 -> -0.071796149
A22: W37 | B22: Enterprise Value(EV)
C23: 2024 | E23: 2023
B24: Equity Value | C24: 180168 | E24: 188362 | G24: W1 Financial Structure analysis
B25: Net Debt Value | C25: 38809 | E25: 43542 | G25: W1 Financial Structure analysis
B26: Enterprise Value | C26: =SUM(C24:C25) -> 218977 | E26: =SUM(E24:E25) -> 231904
A30: W38 | B30: Cash-based Valuation
C31: 2024 | E31: 2023
B32: FCF | C32: ='3. Cash flow analysis'!D126 -> 39532 | E32: ='3. Cash flow analysis'!F126 -> 36457
B33: FCF yield | C33: ='3. Cash flow analysis'!E130 -> 0.1633628 | E33: ='3. Cash flow analysis'!G130 -> 0.13359987
B34: EV/FCF | C34: =C26/C32 -> 5.539234 | E34: =E26/E32 -> 6.3610281
B35: Dividend yield | C35: ='3. Cash flow analysis'!D107/C17 -> 0.044792443 | E35: ='3. Cash flow analysis'!F107/E17 -> 0.040257466
B36: Payout | C36: ='3. Cash flow analysis'!D107/C32 -> 0.21926541 | E36: ='3. Cash flow analysis'!F107/E32 -> 0.23021642
B37: Adjusted EBITDA | C37: 65803 | E37: 68538
B38: EV/EBITDA | C38: =C26/C37 -> 3.3277662 | E38: =E26/E37 -> 3.3835828
B39: Implied EV (at 2023 multiple) | C39: =C37*E38 -> 222649.9

Sheet 4.AR Screenshot
A2: 4. CFA Valuation screenshot
